buildmaster
tasks
