Metadata-Version: 1.1
Name: buildmaster
Version: 0.20.4
Summary: web-based management system builder
Home-page: https://gitee.com/rushmore/buildmaster
Author: Rushmore (Leiming Hong)
Author-email: hong.leiming@qq.com
License: LGPL
Keywords: DB
Platform: UNKNOWN
Classifier: Intended Audience :: Developers
Classifier: Topic :: Software Development :: Libraries :: Python Modules
Classifier: License :: OSI Approved :: MIT License
Classifier: Programming Language :: Python :: 3.7
